Workbook

Sheet 01_3月经营总表
A1: 江苏万友上海阿维塔 2026年3月经营目标（简化执行版）
A2: 数据来源：门店及AC明细表0301（上海门店、人员、3月车型销量、单店费用）
A4: 一、3月核心经营指标（蓝色可调整）
A5: 3月销售目标（台） | B5: 150 | C5: 默认引用3月门店合计销量
A6: 其中库存车销售目标（台） | B6: 60 | C6: 默认按40%设置，可调整
A7: 3月目标成交率 | B7: 0.0255 | C7: 沿用模板渠道成交口径
A8: 3月线索目标（条） | B8: =ROUND(B5/B7,0) -> 5882 | C8: 由销量目标反推
A10: 二、分车型销售、库存、毛利、费用、利润
A11: 车型 | B11: 3月销量目标(台) | C11: 库存车目标(台) | D11: 单车成交均价(元) | E11: 单车毛利(元，可手工输入) | F11: 单车变动费用(元) | G11: 单车贡献利润(元) | H11: 毛利总额(元) | I11: 变动费用总额(元) | J11: 贡献利润总额(元) | K11: 说明
A12: 阿维塔06 | B12: 60 | C12: =ROUND(IF($B$5=0,0,B12/$B$5*$B$6),0) -> 24 | D12: 238000 | E12: 11000 | F12: 8500 | G12: =E12-F12 -> 2500 | H12: =B12*E12 -> 660000 | I12: =B12*F12 -> 510000 | J12: =B12*G12 -> 150000 | K12: 3月主销去化（提升毛利结构）
A13: 阿维塔07 | B13: 75 | C13: =ROUND(IF($B$5=0,0,B13/$B$5*$B$6),0) -> 30 | D13: 268000 | E13: 20000 | F13: 9000 | G13: =E13-F13 -> 11000 | H13: =B13*E13 -> 1500000 | I13: =B13*F13 -> 675000 | J13: =B13*G13 -> 825000 | K13: 3月主销车型（提升成交质量）
A14: 阿维塔11 | B14: 0 | C14: =ROUND(IF($B$5=0,0,B14/$B$5*$B$6),0) -> 0 | D14: 305000 | E14: 12000 | F14: 8500 | G14: =E14-F14 -> 3500 | H14: =B14*E14 -> 0 | I14: =B14*F14 -> 0 | J14: =B14*G14 -> 0 | K14: 3月老款清库（保利润）
A15: 阿维塔12 | B15: 15 | C15: =$B$6-SUM(C12:C14) -> 6 | D15: 328000 | E15: 11000 | F15: 9000 | G15: =E15-F15 -> 2000 | H15: =B15*E15 -> 165000 | I15: =B15*F15 -> 135000 | J15: =B15*G15 -> 30000 | K15: 3月高配成交（利润补位）
A16: 合计 | B16: =SUM(B12:B15) -> 150 | C16: =SUM(C12:C15) -> 60 | G16: =IF(B16=0,0,J16/B16) -> 6700 | H16: =SUM(H12:H15) -> 2325000 | I16: =SUM(I12:I15) -> 1320000 | J16: =SUM(J12:J15) -> 1005000
A18: 三、费用与利润汇总
A19: 销售收入（估算） | B19: =SUMPRODUCT(B12:B15,D12:D15) -> 39300000
A20: 车型贡献利润（毛利-变动费用） | B20: =J16 -> 1005000
A21: 门店固定费用（来自明细表） | B21: =163.23*10000 -> 1632300
A22: 预计经营利润（扣门店固定费用） | B22: =B20-B21 -> -627300
A23: 单车经营利润 | B23: =IF(B16=0,0,B22/B16) -> -4182

Sheet 02_线索来源分解
A1: 3月线索来源与门店分解（上海版）
A2: 渠道口径：沿用模板渠道结构；门店目标与费用：导入门店及AC明细表0301。
A4: 一、渠道级3月目标
A5: 渠道 | B5: 来源线索 | C5: 来源订单 | D5: 来源成交率 | E5: 线索占比 | F5: 3月线索目标 | G5: 3月订单目标 | H5: 目标成交率 | I5: 建议CPL | J5: 预算(元) | K5: 负责人
A6: 厂家渠道线索 | B6: 6061 | C6: 200 | D6: 0.033 | E6: =IF($B$22=0,0,B6/$B$22) -> 0.13998014 | F6: =ROUND('01_3月经营总表'!$B$8*E6,0) -> 823 | G6: =ROUND('01_3月经营总表'!$B$5*IF($C$22=0,0,C6/$C$22),0) -> 27 | H6: =IF(F6=0,0,G6/F6) -> 0.032806804 | I6: 85 | J6: =F6*I6 -> 69955 | K6: 厂家对接岗
A7: 自然进店 | B7: 3776 | C7: 185 | D7: 0.049 | E7: =IF($B$22=0,0,B7/$B$22) -> 0.087207557 | F7: =ROUND('01_3月经营总表'!$B$8*E7,0) -> 513 | G7: =ROUND('01_3月经营总表'!$B$5*IF($C$22=0,0,C7/$C$22),0) -> 25 | H7: =IF(F7=0,0,G7/F7) -> 0.048732943 | I7: 60 | J7: =F7*I7 -> 30780 | K7: 门店销售经理
A8: 快闪展示/车展 | B8: 4822 | C8: 135 | D8: 0.028 | E8: =IF($B$22=0,0,B8/$B$22) -> 0.11136516 | F8: =ROUND('01_3月经营总表'!$B$8*E8,0) -> 655 | G8: =ROUND('01_3月经营总表'!$B$5*IF($C$22=0,0,C8/$C$22),0) -> 18 | H8: =IF(F8=0,0,G8/F8) -> 0.027480916 | I8: 180 | J8: =F8*I8 -> 117900 | K8: 市场活动经理
A9: 三方平台 | B9: 6000 | C9: 110 | D9: 0.018333333 | E9: =IF($B$22=0,0,B9/$B$22) -> 0.13857133 | F9: =ROUND('01_3月经营总表'!$B$8*E9,0) -> 815 | G9: =ROUND('01_3月经营总表'!$B$5*IF($C$22=0,0,C9/$C$22),0) -> 15 | H9: =IF(F9=0,0,G9/F9) -> 0.018404908 | I9: 220 | J9: =F9*I9 -> 179300 | K9: 线索运营
A10: 老客户带新 | B10: 667 | C10: 100 | D10: 0.15 | E10: =IF($B$22=0,0,B10/$B$22) -> 0.015404513 | F10: =ROUND('01_3月经营总表'!$B$8*E10,0) -> 91 | G10: =ROUND('01_3月经营总表'!$B$5*IF($C$22=0,0,C10/$C$22),0) -> 14 | H10: =IF(F10=0,0,G10/F10) -> 0.15384615 | I10: 50 | J10: =F10*I10 -> 4550 | K10: CRM专员
A11: 新媒体 | B11: 11112 | C11: 100 | D11: 0.009 | E11: =IF($B$22=0,0,B11/$B$22) -> 0.2566341 | F11: =ROUND('01_3月经营总表'!$B$8*E11,0) -> 1510 | G11: =ROUND('01_3月经营总表'!$B$5*IF($C$22=0,0,C11/$C$22),0) -> 14 | H11: =IF(F11=0,0,G11/F11) -> 0.0092715232 | I11: 120 | J11: =F11*I11 -> 181200 | K11: 新媒体主管
A12: 市场活动 | B12: 3600 | C12: 90 | D12: 0.025 | E12: =IF($B$22=0,0,B12/$B$22) -> 0.083142798 | F12: =ROUND('01_3月经营总表'!$B$8*E12,0) -> 489 | G12: =ROUND('01_3月经营总表'!$B$5*IF($C$22=0,0,C12/$C$22),0) -> 12 | H12: =IF(F12=0,0,G12/F12) -> 0.024539877 | I12: 180 | J12: =F12*I12 -> 88020 | K12: 市场活动经理
A13: 大客户矩阵 | B13: 550 | C13: 55 | D13: 0.1 | E13: =IF($B$22=0,0,B13/$B$22) -> 0.012702372 | F13: =ROUND('01_3月经营总表'!$B$8*E13,0) -> 75 | G13: =ROUND('01_3月经营总表'!$B$5*IF($C$22=0,0,C13/$C$22),0) -> 7 | H13: =IF(F13=0,0,G13/F13) -> 0.093333333 | I13: 100 | J13: =F13*I13 -> 7500 | K13: 大客户经理
A14: 区域展示活动 | B14: 1200 | C14: 30 | D14: 0.025 | E14: =IF($B$22=0,0,B14/$B$22) -> 0.027714266 | F14: =ROUND('01_3月经营总表'!$B$8*E14,0) -> 163 | G14: =ROUND('01_3月经营总表'!$B$5*IF($C$22=0,0,C14/$C$22),0) -> 4 | H14: =IF(F14=0,0,G14/F14) -> 0.024539877 | I14: 150 | J14: =F14*I14 -> 24450 | K14: 区域市场
A15: 社区园区推广 | B15: 1297 | C15: 35 | D15: 0.027 | E15: =IF($B$22=0,0,B15/$B$22) -> 0.029954502 | F15: =ROUND('01_3月经营总表'!$B$8*E15,0) -> 176 | G15: =ROUND('01_3月经营总表'!$B$5*IF($C$22=0,0,C15/$C$22),0) -> 5 | H15: =IF(F15=0,0,G15/F15) -> 0.028409091 | I15: 130 | J15: =F15*I15 -> 22880 | K15: 地推主管
A16: 交付售后回流介绍 | B16: 280 | C16: 14 | D16: 0.05 | E16: =IF($B$22=0,0,B16/$B$22) -> 0.006466662 | F16: =ROUND('01_3月经营总表'!$B$8*E16,0) -> 38 | G16: =ROUND('01_3月经营总表'!$B$5*IF($C$22=0,0,C16/$C$22),0) -> 2 | H16: =IF(F16=0,0,G16/F16) -> 0.052631579 | I16: 40 | J16: =F16*I16 -> 1520 | K16: 交付/售后主管
A17: 异业联盟 | B17: 858 | C17: 12 | D17: 0.014 | E17: =IF($B$22=0,0,B17/$B$22) -> 0.0198157 | F17: =ROUND('01_3月经营总表'!$B$8*E17,0) -> 117 | G17: =ROUND('01_3月经营总表'!$B$5*IF($C$22=0,0,C17/$C$22),0) -> 2 | H17: =IF(F17=0,0,G17/F17) -> 0.017094017 | I17: 160 | J17: =F17*I17 -> 18720 | K17: 异业BD
... A21: 美团+大众点评 | B21: 910 | C21: 10 | D21: 0.011 | E21: =IF($B$22=0,0,B21/$B$22) -> 0.021016652 | F21: =ROUND('01_3月经营总表'!$B$8*E21,0) -> 124 | G21: =ROUND('01_3月经营总表'!$B$5*IF($C$22=0,0,C21/$C$22),0) -> 1 | H21: =IF(F21=0,0,G21/F21) -> 0.0080645161 | I21: 90 | J21: =F21*I21 -> 11160 | K21: 门店运营
A22: 合计 | B22: =SUM(B6:B21) -> 43299 | C22: =SUM(C6:C21) -> 1106 | D22: =IF(B22=0,0,C22/B22) -> 0.025543315 | E22: =SUM(E6:E21) -> 1 | F22: =SUM(F6:F21) -> 5884 | G22: =SUM(G6:G21) -> 149 | H22: =IF(F22=0,0,G22/F22) -> 0.02532291 | I22: =IF(F22=0,0,J22/F22) -> 137.06577 | J22: =SUM(J6:J21) -> 806495
A24: 二、门店目标与费用明细（导入明细表）
A25: 门店 | B25: 3月销量(台) | C25: 3月销量目标(台) | D25: 库存车目标(台) | E25: 3月线索目标(条) | F25: 单店费用(万元) | G25: 单店费用(元) | H25: 单车固定费用(元/台) | I25: 厂家渠道 | J25: 自然进店 | K25: 快闪/车展 | L25: 三方平台 | M25: 老带新 | N25: 新媒体 | O25: 市场活动 | P25: 大客户 | Q25: 区域活动 | R25: 社区园区 | S25: 交付回流 | T25: 异业联盟 | U25: 其他渠道 | V25: 负责人
A26: 上海车市店 | B26: 26 | C26: 26 | D26: =ROUND(C26*0.4,0) -> 10 | E26: =ROUND('01_3月经营总表'!$B$8*IF('01_3月经营总表'!$B$5=0,0,C26/'01_3月经营总表'!$B$5),0) -> 1020 | F26: 17.44 | G26: =F26*10000 -> 174400 | H26: =IF(C26=0,0,G26/C26) -> 6707.6923 | I26: =ROUND(E26*$F$6/$F$22,0) -> 143 | J26: =ROUND(E26*$F$7/$F$22,0) -> 89 | K26: =ROUND(E26*$F$8/$F$22,0) -> 114 | L26: =ROUND(E26*$F$9/$F$22,0) -> 141 | M26: =ROUND(E26*$F$10/$F$22,0) -> 16 | N26: =ROUND(E26*$F$11/$F$22,0) -> 262 | O26: =ROUND(E26*$F$12/$F$22,0) -> 85 | P26: =ROUND(E26*$F$13/$F$22,0) -> 13 | Q26: =ROUND(E26*$F$14/$F$22,0) -> 28 | R26: =ROUND(E26*$F$15/$F$22,0) -> 31 | S26: =ROUND(E26*$F$16/$F$22,0) -> 7 | T26: =ROUND(E26*$F$17/$F$22,0) -> 20 | U26: =E26-SUM(I26:T26) -> 71 | V26: 店长
A27: 上海茸兴店 | B27: 32 | C27: 32 | D27: =ROUND(C27*0.4,0) -> 13 | E27: =ROUND('01_3月经营总表'!$B$8*IF('01_3月经营总表'!$B$5=0,0,C27/'01_3月经营总表'!$B$5),0) -> 1255 | F27: 23.52 | G27: =F27*10000 -> 235200 | H27: =IF(C27=0,0,G27/C27) -> 7350 | I27: =ROUND(E27*$F$6/$F$22,0) -> 176 | J27: =ROUND(E27*$F$7/$F$22,0) -> 109 | K27: =ROUND(E27*$F$8/$F$22,0) -> 140 | L27: =ROUND(E27*$F$9/$F$22,0) -> 174 | M27: =ROUND(E27*$F$10/$F$22,0) -> 19 | N27: =ROUND(E27*$F$11/$F$22,0) -> 322 | O27: =ROUND(E27*$F$12/$F$22,0) -> 104 | P27: =ROUND(E27*$F$13/$F$22,0) -> 16 | Q27: =ROUND(E27*$F$14/$F$22,0) -> 35 | R27: =ROUND(E27*$F$15/$F$22,0) -> 38 | S27: =ROUND(E27*$F$16/$F$22,0) -> 8 | T27: =ROUND(E27*$F$17/$F$22,0) -> 25 | U27: =E27-SUM(I27:T27) -> 89 | V27: 店长
A28: 上海松江店 | B28: 50 | C28: 50 | D28: =ROUND(C28*0.4,0) -> 20 | E28: =ROUND('01_3月经营总表'!$B$8*IF('01_3月经营总表'!$B$5=0,0,C28/'01_3月经营总表'!$B$5),0) -> 1961 | F28: 80.64 | G28: =F28*10000 -> 806400 | H28: =IF(C28=0,0,G28/C28) -> 16128 | I28: =ROUND(E28*$F$6/$F$22,0) -> 274 | J28: =ROUND(E28*$F$7/$F$22,0) -> 171 | K28: =ROUND(E28*$F$8/$F$22,0) -> 218 | L28: =ROUND(E28*$F$9/$F$22,0) -> 272 | M28: =ROUND(E28*$F$10/$F$22,0) -> 30 | N28: =ROUND(E28*$F$11/$F$22,0) -> 503 | O28: =ROUND(E28*$F$12/$F$22,0) -> 163 | P28: =ROUND(E28*$F$13/$F$22,0) -> 25 | Q28: =ROUND(E28*$F$14/$F$22,0) -> 54 | R28: =ROUND(E28*$F$15/$F$22,0) -> 59 | S28: =ROUND(E28*$F$16/$F$22,0) -> 13 | T28: =ROUND(E28*$F$17/$F$22,0) -> 39 | U28: =E28-SUM(I28:T28) -> 140 | V28: 店长
A29: 上海龙湖奉贤天街店 | B29: 24 | C29: 24 | D29: =ROUND(C29*0.4,0) -> 10 | E29: =ROUND('01_3月经营总表'!$B$8*IF('01_3月经营总表'!$B$5=0,0,C29/'01_3月经营总表'!$B$5),0) -> 941 | F29: 18.28 | G29: =F29*10000 -> 182800 | H29: =IF(C29=0,0,G29/C29) -> 7616.6667 | I29: =ROUND(E29*$F$6/$F$22,0) -> 132 | J29: =ROUND(E29*$F$7/$F$22,0) -> 82 | K29: =ROUND(E29*$F$8/$F$22,0) -> 105 | L29: =ROUND(E29*$F$9/$F$22,0) -> 130 | M29: =ROUND(E29*$F$10/$F$22,0) -> 15 | N29: =ROUND(E29*$F$11/$F$22,0) -> 241 | O29: =ROUND(E29*$F$12/$F$22,0) -> 78 | P29: =ROUND(E29*$F$13/$F$22,0) -> 12 | Q29: =ROUND(E29*$F$14/$F$22,0) -> 26 | R29: =ROUND(E29*$F$15/$F$22,0) -> 28 | S29: =ROUND(E29*$F$16/$F$22,0) -> 6 | T29: =ROUND(E29*$F$17/$F$22,0) -> 19 | U29: =E29-SUM(I29:T29) -> 67 | V29: 店长
A30: 上海沪青平店 | B30: 12 | C30: 12 | D30: =ROUND(C30*0.4,0) -> 5 | E30: =ROUND('01_3月经营总表'!$B$8*IF('01_3月经营总表'!$B$5=0,0,C30/'01_3月经营总表'!$B$5),0) -> 471 | F30: 10 | G30: =F30*10000 -> 100000 | H30: =IF(C30=0,0,G30/C30) -> 8333.3333 | I30: =ROUND(E30*$F$6/$F$22,0) -> 66 | J30: =ROUND(E30*$F$7/$F$22,0) -> 41 | K30: =ROUND(E30*$F$8/$F$22,0) -> 52 | L30: =ROUND(E30*$F$9/$F$22,0) -> 65 | M30: =ROUND(E30*$F$10/$F$22,0) -> 7 | N30: =ROUND(E30*$F$11/$F$22,0) -> 121 | O30: =ROUND(E30*$F$12/$F$22,0) -> 39 | P30: =ROUND(E30*$F$13/$F$22,0) -> 6 | Q30: =ROUND(E30*$F$14/$F$22,0) -> 13 | R30: =ROUND(E30*$F$15/$F$22,0) -> 14 | S30: =ROUND(E30*$F$16/$F$22,0) -> 3 | T30: =ROUND(E30*$F$17/$F$22,0) -> 9 | U30: =E30-SUM(I30:T30) -> 35 | V30: 店长
A31: 上海中春店 | B31: 6 | C31: 6 | D31: =ROUND(C31*0.4,0) -> 2 | E31: =ROUND('01_3月经营总表'!$B$8*IF('01_3月经营总表'!$B$5=0,0,C31/'01_3月经营总表'!$B$5),0) -> 235 | F31: 13.35 | G31: =F31*10000 -> 133500 | H31: =IF(C31=0,0,G31/C31) -> 22250 | I31: =ROUND(E31*$F$6/$F$22,0) -> 33 | J31: =ROUND(E31*$F$7/$F$22,0) -> 20 | K31: =ROUND(E31*$F$8/$F$22,0) -> 26 | L31: =ROUND(E31*$F$9/$F$22,0) -> 33 | M31: =ROUND(E31*$F$10/$F$22,0) -> 4 | N31: =ROUND(E31*$F$11/$F$22,0) -> 60 | O31: =ROUND(E31*$F$12/$F$22,0) -> 20 | P31: =ROUND(E31*$F$13/$F$22,0) -> 3 | Q31: =ROUND(E31*$F$14/$F$22,0) -> 7 | R31: =ROUND(E31*$F$15/$F$22,0) -> 7 | S31: =ROUND(E31*$F$16/$F$22,0) -> 2 | T31: =ROUND(E31*$F$17/$F$22,0) -> 5 | U31: =E31-SUM(I31:T31) -> 15 | V31: 店长
A32: 合计 | B32: =SUM(B26:B31) -> 150 | C32: =SUM(C26:C31) -> 150 | D32: =SUM(D26:D31) -> 60 | E32: =SUM(E26:E31) -> 5883 | F32: =SUM(F26:F31) -> 163.23 | G32: =SUM(G26:G31) -> 1632300 | H32: =SUM(H26:H31) -> 68385.692 | I32: =SUM(I26:I31) -> 824 | ... U32: =SUM(U26:U31) -> 417

Sheet 03_门店顾问分解
A1: 门店-销售顾问目标与利润分解（上海版）
A2: 数据来源：门店及AC明细表0301；3月车型销量默认转为3月个人目标，可按实际调整。
A4: 一、销售顾问分解（蓝色可调整）
A5: 门店 | B5: 销售顾问 | C5: 3月07 | D5: 3月06 | E5: 3月12 | F5: 3月合计 | G5: 3月07目标 | H5: 3月06目标 | I5: 3月12目标 | J5: 3月合计目标 | K5: 个人线索目标 | L5: 个人库存目标 | M5: 单车毛利 | N5: 单车变动费用 | O5: 单车贡献利润 | P5: 贡献利润总额 | Q5: 分摊门店费用 | R5: 预计经营利润 | S5: 备注
A6: 上海车市店 | B6: 梁会方 | C6: 4 | D6: 2 | E6: 1 | F6: 7 | G6: 4 | H6: 2 | I6: 1 | J6: =SUM(G6:I6) -> 7 | K6: =ROUND(IFERROR(VLOOKUP(A6,'02_线索来源分解'!$A$26:$E$200,5,0)*J6/VLOOKUP(A6,'02_线索来源分解'!$A$26:$E$200,3,0),0),0) -> 275 | L6: =ROUND(IFERROR(VLOOKUP(A6,'02_线索来源分解'!$A$26:$D$200,4,0)*J6/VLOOKUP(A6,'02_线索来源分解'!$A$26:$D$200,3,0),0),0) -> 3 | M6: =IF(J6=0,0,(G6*'01_3月经营总表'!$E$13+H6*'01_3月经营总表'!$E$12+I6*'01_3月经营总表'!$E$15)/J6) -> 16142.857 | N6: =IF(J6=0,0,(G6*'01_3月经营总表'!$F$13+H6*'01_3月经营总表'!$F$12+I6*'01_3月经营总表'!$F$15)/J6) -> 8857.1429 | O6: =M6-N6 -> 7285.7143 | P6: =J6*O6 -> 51000 | Q6: =IFERROR(VLOOKUP(A6,'02_线索来源分解'!$A$26:$G$200,7,0)*J6/VLOOKUP(A6,'02_线索来源分解'!$A$26:$G$200,3,0),0) -> 46953.846 | R6: =P6-Q6 -> 4046.1538 | S6: 每周五复盘
A7: 上海车市店 | B7: 王毅洋 | C7: 3 | D7: 3 | E7: 1 | F7: 7 | G7: 3 | H7: 3 | I7: 1 | J7: =SUM(G7:I7) -> 7 | K7: =ROUND(IFERROR(VLOOKUP(A7,'02_线索来源分解'!$A$26:$E$200,5,0)*J7/VLOOKUP(A7,'02_线索来源分解'!$A$26:$E$200,3,0),0),0) -> 275 | L7: =ROUND(IFERROR(VLOOKUP(A7,'02_线索来源分解'!$A$26:$D$200,4,0)*J7/VLOOKUP(A7,'02_线索来源分解'!$A$26:$D$200,3,0),0),0) -> 3 | M7: =IF(J7=0,0,(G7*'01_3月经营总表'!$E$13+H7*'01_3月经营总表'!$E$12+I7*'01_3月经营总表'!$E$15)/J7) -> 14857.143 | N7: =IF(J7=0,0,(G7*'01_3月经营总表'!$F$13+H7*'01_3月经营总表'!$F$12+I7*'01_3月经营总表'!$F$15)/J7) -> 8785.7143 | O7: =M7-N7 -> 6071.4286 | P7: =J7*O7 -> 42500 | Q7: =IFERROR(VLOOKUP(A7,'02_线索来源分解'!$A$26:$G$200,7,0)*J7/VLOOKUP(A7,'02_线索来源分解'!$A$26:$G$200,3,0),0) -> 46953.846 | R7: =P7-Q7 -> -4453.8462 | S7: 每周五复盘
A8: 上海车市店 | B8: 马星晨 | C8: 3 | D8: 3 | E8: 0 | F8: 6 | G8: 3 | H8: 3 | I8: 0 | J8: =SUM(G8:I8) -> 6 | K8: =ROUND(IFERROR(VLOOKUP(A8,'02_线索来源分解'!$A$26:$E$200,5,0)*J8/VLOOKUP(A8,'02_线索来源分解'!$A$26:$E$200,3,0),0),0) -> 235 | L8: =ROUND(IFERROR(VLOOKUP(A8,'02_线索来源分解'!$A$26:$D$200,4,0)*J8/VLOOKUP(A8,'02_线索来源分解'!$A$26:$D$200,3,0),0),0) -> 2 | M8: =IF(J8=0,0,(G8*'01_3月经营总表'!$E$13+H8*'01_3月经营总表'!$E$12+I8*'01_3月经营总表'!$E$15)/J8) -> 15500 | N8: =IF(J8=0,0,(G8*'01_3月经营总表'!$F$13+H8*'01_3月经营总表'!$F$12+I8*'01_3月经营总表'!$F$15)/J8) -> 8750 | O8: =M8-N8 -> 6750 | P8: =J8*O8 -> 40500 | Q8: =IFERROR(VLOOKUP(A8,'02_线索来源分解'!$A$26:$G$200,7,0)*J8/VLOOKUP(A8,'02_线索来源分解'!$A$26:$G$200,3,0),0) -> 40246.154 | R8: =P8-Q8 -> 253.84615 | S8: 每周五复盘
A9: 上海车市店 | B9: 王明龙 | C9: 3 | D9: 2 | E9: 1 | F9: 6 | G9: 3 | H9: 2 | I9: 1 | J9: =SUM(G9:I9) -> 6 | K9: =ROUND(IFERROR(VLOOKUP(A9,'02_线索来源分解'!$A$26:$E$200,5,0)*J9/VLOOKUP(A9,'02_线索来源分解'!$A$26:$E$200,3,0),0),0) -> 235 | L9: =ROUND(IFERROR(VLOOKUP(A9,'02_线索来源分解'!$A$26:$D$200,4,0)*J9/VLOOKUP(A9,'02_线索来源分解'!$A$26:$D$200,3,0),0),0) -> 2 | M9: =IF(J9=0,0,(G9*'01_3月经营总表'!$E$13+H9*'01_3月经营总表'!$E$12+I9*'01_3月经营总表'!$E$15)/J9) -> 15500 | N9: =IF(J9=0,0,(G9*'01_3月经营总表'!$F$13+H9*'01_3月经营总表'!$F$12+I9*'01_3月经营总表'!$F$15)/J9) -> 8833.3333 | O9: =M9-N9 -> 6666.6667 | P9: =J9*O9 -> 40000 | Q9: =IFERROR(VLOOKUP(A9,'02_线索来源分解'!$A$26:$G$200,7,0)*J9/VLOOKUP(A9,'02_线索来源分解'!$A$26:$G$200,3,0),0) -> 40246.154 | R9: =P9-Q9 -> -246.15385 | S9: 每周五复盘
A10: 上海茸兴店 | B10: 李宋坚 | C10: 4 | D10: 2 | E10: 1 | F10: 7 | G10: 4 | H10: 2 | I10: 1 | J10: =SUM(G10:I10) -> 7 | K10: =ROUND(IFERROR(VLOOKUP(A10,'02_线索来源分解'!$A$26:$E$200,5,0)*J10/VLOOKUP(A10,'02_线索来源分解'!$A$26:$E$200,3,0),0),0) -> 275 | L10: =ROUND(IFERROR(VLOOKUP(A10,'02_线索来源分解'!$A$26:$D$200,4,0)*J10/VLOOKUP(A10,'02_线索来源分解'!$A$26:$D$200,3,0),0),0) -> 3 | M10: =IF(J10=0,0,(G10*'01_3月经营总表'!$E$13+H10*'01_3月经营总表'!$E$12+I10*'01_3月经营总表'!$E$15)/J10) -> 16142.857 | N10: =IF(J10=0,0,(G10*'01_3月经营总表'!$F$13+H10*'01_3月经营总表'!$F$12+I10*'01_3月经营总表'!$F$15)/J10) -> 8857.1429 | O10: =M10-N10 -> 7285.7143 | P10: =J10*O10 -> 51000 | Q10: =IFERROR(VLOOKUP(A10,'02_线索来源分解'!$A$26:$G$200,7,0)*J10/VLOOKUP(A10,'02_线索来源分解'!$A$26:$G$200,3,0),0) -> 51450 | R10: =P10-Q10 -> -450 | S10: 每周五复盘
A11: 上海茸兴店 | B11: 顾浩 | C11: 3 | D11: 3 | E11: 1 | F11: 7 | G11: 3 | H11: 3 | I11: 1 | J11: =SUM(G11:I11) -> 7 | K11: =ROUND(IFERROR(VLOOKUP(A11,'02_线索来源分解'!$A$26:$E$200,5,0)*J11/VLOOKUP(A11,'02_线索来源分解'!$A$26:$E$200,3,0),0),0) -> 275 | L11: =ROUND(IFERROR(VLOOKUP(A11,'02_线索来源分解'!$A$26:$D$200,4,0)*J11/VLOOKUP(A11,'02_线索来源分解'!$A$26:$D$200,3,0),0),0) -> 3 | M11: =IF(J11=0,0,(G11*'01_3月经营总表'!$E$13+H11*'01_3月经营总表'!$E$12+I11*'01_3月经营总表'!$E$15)/J11) -> 14857.143 | N11: =IF(J11=0,0,(G11*'01_3月经营总表'!$F$13+H11*'01_3月经营总表'!$F$12+I11*'01_3月经营总表'!$F$15)/J11) -> 8785.7143 | O11: =M11-N11 -> 6071.4286 | P11: =J11*O11 -> 42500 | Q11: =IFERROR(VLOOKUP(A11,'02_线索来源分解'!$A$26:$G$200,7,0)*J11/VLOOKUP(A11,'02_线索来源分解'!$A$26:$G$200,3,0),0) -> 51450 | R11: =P11-Q11 -> -8950 | S11: 每周五复盘
A12: 上海茸兴店 | B12: 符陆彬 | C12: 4 | D12: 2 | E12: 1 | F12: 7 | G12: 4 | H12: 2 | I12: 1 | J12: =SUM(G12:I12) -> 7 | K12: =ROUND(IFERROR(VLOOKUP(A12,'02_线索来源分解'!$A$26:$E$200,5,0)*J12/VLOOKUP(A12,'02_线索来源分解'!$A$26:$E$200,3,0),0),0) -> 275 | L12: =ROUND(IFERROR(VLOOKUP(A12,'02_线索来源分解'!$A$26:$D$200,4,0)*J12/VLOOKUP(A12,'02_线索来源分解'!$A$26:$D$200,3,0),0),0) -> 3 | M12: =IF(J12=0,0,(G12*'01_3月经营总表'!$E$13+H12*'01_3月经营总表'!$E$12+I12*'01_3月经营总表'!$E$15)/J12) -> 16142.857 | N12: =IF(J12=0,0,(G12*'01_3月经营总表'!$F$13+H12*'01_3月经营总表'!$F$12+I12*'01_3月经营总表'!$F$15)/J12) -> 8857.1429 | O12: =M12-N12 -> 7285.7143 | P12: =J12*O12 -> 51000 | Q12: =IFERROR(VLOOKUP(A12,'02_线索来源分解'!$A$26:$G$200,7,0)*J12/VLOOKUP(A12,'02_线索来源分解'!$A$26:$G$200,3,0),0) -> 51450 | R12: =P12-Q12 -> -450 | S12: 每周五复盘
A13: 上海茸兴店 | B13: 高宏展 | C13: 3 | D13: 3 | E13: 0 | F13: 6 | G13: 3 | H13: 3 | I13: 0 | J13: =SUM(G13:I13) -> 6 | K13: =ROUND(IFERROR(VLOOKUP(A13,'02_线索来源分解'!$A$26:$E$200,5,0)*J13/VLOOKUP(A13,'02_线索来源分解'!$A$26:$E$200,3,0),0),0) -> 235 | L13: =ROUND(IFERROR(VLOOKUP(A13,'02_线索来源分解'!$A$26:$D$200,4,0)*J13/VLOOKUP(A13,'02_线索来源分解'!$A$26:$D$200,3,0),0),0) -> 2 | M13: =IF(J13=0,0,(G13*'01_3月经营总表'!$E$13+H13*'01_3月经营总表'!$E$12+I13*'01_3月经营总表'!$E$15)/J13) -> 15500 | N13: =IF(J13=0,0,(G13*'01_3月经营总表'!$F$13+H13*'01_3月经营总表'!$F$12+I13*'01_3月经营总表'!$F$15)/J13) -> 8750 | O13: =M13-N13 -> 6750 | P13: =J13*O13 -> 40500 | Q13: =IFERROR(VLOOKUP(A13,'02_线索来源分解'!$A$26:$G$200,7,0)*J13/VLOOKUP(A13,'02_线索来源分解'!$A$26:$G$200,3,0),0) -> 44100 | R13: =P13-Q13 -> -3600 | S13: 每周五复盘
A14: 上海茸兴店 | B14: 田汨龙 | C14: 3 | D14: 2 | E14: 0 | F14: 5 | G14: 3 | H14: 2 | I14: 0 | J14: =SUM(G14:I14) -> 5 | K14: =ROUND(IFERROR(VLOOKUP(A14,'02_线索来源分解'!$A$26:$E$200,5,0)*J14/VLOOKUP(A14,'02_线索来源分解'!$A$26:$E$200,3,0),0),0) -> 196 | L14: =ROUND(IFERROR(VLOOKUP(A14,'02_线索来源分解'!$A$26:$D$200,4,0)*J14/VLOOKUP(A14,'02_线索来源分解'!$A$26:$D$200,3,0),0),0) -> 2 | M14: =IF(J14=0,0,(G14*'01_3月经营总表'!$E$13+H14*'01_3月经营总表'!$E$12+I14*'01_3月经营总表'!$E$15)/J14) -> 16400 | N14: =IF(J14=0,0,(G14*'01_3月经营总表'!$F$13+H14*'01_3月经营总表'!$F$12+I14*'01_3月经营总表'!$F$15)/J14) -> 8800 | O14: =M14-N14 -> 7600 | P14: =J14*O14 -> 38000 | Q14: =IFERROR(VLOOKUP(A14,'02_线索来源分解'!$A$26:$G$200,7,0)*J14/VLOOKUP(A14,'02_线索来源分解'!$A$26:$G$200,3,0),0) -> 36750 | R14: =P14-Q14 -> 1250 | S14: 每周五复盘
A15: 上海松江店 | B15: 武利海 | C15: 5 | D15: 4 | E15: 1 | F15: 10 | G15: 5 | H15: 4 | I15: 1 | J15: =SUM(G15:I15) -> 10 | K15: =ROUND(IFERROR(VLOOKUP(A15,'02_线索来源分解'!$A$26:$E$200,5,0)*J15/VLOOKUP(A15,'02_线索来源分解'!$A$26:$E$200,3,0),0),0) -> 392 | L15: =ROUND(IFERROR(VLOOKUP(A15,'02_线索来源分解'!$A$26:$D$200,4,0)*J15/VLOOKUP(A15,'02_线索来源分解'!$A$26:$D$200,3,0),0),0) -> 4 | M15: =IF(J15=0,0,(G15*'01_3月经营总表'!$E$13+H15*'01_3月经营总表'!$E$12+I15*'01_3月经营总表'!$E$15)/J15) -> 15500 | N15: =IF(J15=0,0,(G15*'01_3月经营总表'!$F$13+H15*'01_3月经营总表'!$F$12+I15*'01_3月经营总表'!$F$15)/J15) -> 8800 | O15: =M15-N15 -> 6700 | P15: =J15*O15 -> 67000 | Q15: =IFERROR(VLOOKUP(A15,'02_线索来源分解'!$A$26:$G$200,7,0)*J15/VLOOKUP(A15,'02_线索来源分解'!$A$26:$G$200,3,0),0) -> 161280 | R15: =P15-Q15 -> -94280 | S15: 每周五复盘
A16: 上海松江店 | B16: 黄大海 | C16: 5 | D16: 4 | E16: 1 | F16: 10 | G16: 5 | H16: 4 | I16: 1 | J16: =SUM(G16:I16) -> 10 | K16: =ROUND(IFERROR(VLOOKUP(A16,'02_线索来源分解'!$A$26:$E$200,5,0)*J16/VLOOKUP(A16,'02_线索来源分解'!$A$26:$E$200,3,0),0),0) -> 392 | L16: =ROUND(IFERROR(VLOOKUP(A16,'02_线索来源分解'!$A$26:$D$200,4,0)*J16/VLOOKUP(A16,'02_线索来源分解'!$A$26:$D$200,3,0),0),0) -> 4 | M16: =IF(J16=0,0,(G16*'01_3月经营总表'!$E$13+H16*'01_3月经营总表'!$E$12+I16*'01_3月经营总表'!$E$15)/J16) -> 15500 | N16: =IF(J16=0,0,(G16*'01_3月经营总表'!$F$13+H16*'01_3月经营总表'!$F$12+I16*'01_3月经营总表'!$F$15)/J16) -> 8800 | O16: =M16-N16 -> 6700 | P16: =J16*O16 -> 67000 | Q16: =IFERROR(VLOOKUP(A16,'02_线索来源分解'!$A$26:$G$200,7,0)*J16/VLOOKUP(A16,'02_线索来源分解'!$A$26:$G$200,3,0),0) -> 161280 | R16: =P16-Q16 -> -94280 | S16: 每周五复盘
A17: 上海松江店 | B17: 高荟萃 | C17: 5 | D17: 4 | E17: 1 | F17: 10 | G17: 5 | H17: 4 | I17: 1 | J17: =SUM(G17:I17) -> 10 | K17: =ROUND(IFERROR(VLOOKUP(A17,'02_线索来源分解'!$A$26:$E$200,5,0)*J17/VLOOKUP(A17,'02_线索来源分解'!$A$26:$E$200,3,0),0),0) -> 392 | L17: =ROUND(IFERROR(VLOOKUP(A17,'02_线索来源分解'!$A$26:$D$200,4,0)*J17/VLOOKUP(A17,'02_线索来源分解'!$A$26:$D$200,3,0),0),0) -> 4 | M17: =IF(J17=0,0,(G17*'01_3月经营总表'!$E$13+H17*'01_3月经营总表'!$E$12+I17*'01_3月经营总表'!$E$15)/J17) -> 15500 | N17: =IF(J17=0,0,(G17*'01_3月经营总表'!$F$13+H17*'01_3月经营总表'!$F$12+I17*'01_3月经营总表'!$F$15)/J17) -> 8800 | O17: =M17-N17 -> 6700 | P17: =J17*O17 -> 67000 | Q17: =IFERROR(VLOOKUP(A17,'02_线索来源分解'!$A$26:$G$200,7,0)*J17/VLOOKUP(A17,'02_线索来源分解'!$A$26:$G$200,3,0),0) -> 161280 | R17: =P17-Q17 -> -94280 | S17: 每周五复盘
... A28: 上海中春店 | B28: 鲁平 | C28: 3 | D28: 3 | E28: 0 | F28: 6 | G28: 3 | H28: 3 | I28: 0 | J28: =SUM(G28:I28) -> 6 | K28: =ROUND(IFERROR(VLOOKUP(A28,'02_线索来源分解'!$A$26:$E$200,5,0)*J28/VLOOKUP(A28,'02_线索来源分解'!$A$26:$E$200,3,0),0),0) -> 235 | L28: =ROUND(IFERROR(VLOOKUP(A28,'02_线索来源分解'!$A$26:$D$200,4,0)*J28/VLOOKUP(A28,'02_线索来源分解'!$A$26:$D$200,3,0),0),0) -> 2 | M28: =IF(J28=0,0,(G28*'01_3月经营总表'!$E$13+H28*'01_3月经营总表'!$E$12+I28*'01_3月经营总表'!$E$15)/J28) -> 15500 | N28: =IF(J28=0,0,(G28*'01_3月经营总表'!$F$13+H28*'01_3月经营总表'!$F$12+I28*'01_3月经营总表'!$F$15)/J28) -> 8750 | O28: =M28-N28 -> 6750 | P28: =J28*O28 -> 40500 | Q28: =IFERROR(VLOOKUP(A28,'02_线索来源分解'!$A$26:$G$200,7,0)*J28/VLOOKUP(A28,'02_线索来源分解'!$A$26:$G$200,3,0),0) -> 133500 | R28: =P28-Q28 -> -93000 | S28: 每周五复盘
A30: 二、门店汇总校验
A31: 门店 | B31: 门店目标 | C31: 顾问汇总 | D31: 差异 | E31: 状态 | F31: 门店费用(元) | G31: 顾问分摊费用 | H31: 差异 | I31: 状态 | M31: =IF(J31=0,0,(G31*34000+H31*30000+I31*32000)/J31) -> #VALUE! | N31: =IF(J31=0,0,(G31*9000+H31*8500+I31*9000)/J31) -> #VALUE! | O31: =M31-N31 -> #VALUE! | P31: =J31*O31 -> #VALUE! | Q31: =IFERROR(VLOOKUP(A31,'02_线索来源分解'!$A$26:$G$200,7,0)*J31/VLOOKUP(A31,'02_线索来源分解'!$A$26:$G$200,3,0),0) -> 0 | R31: =P31-Q31 -> #VALUE!
A32: 上海车市店 | B32: =IFERROR(VLOOKUP(A32,'02_线索来源分解'!$A$26:$C$200,3,0),0) -> 26 | C32: =SUMIF($A$6:$A$28,A32,$J$6:$J$28) -> 26 | D32: =C32-B32 -> 0 | E32: =IF(D32=0,"一致","请调整") -> 一致 | F32: =IFERROR(VLOOKUP(A32,'02_线索来源分解'!$A$26:$G$200,7,0),0) -> 174400 | G32: =SUMIF($A$6:$A$28,A32,$Q$6:$Q$28) -> 174400 | H32: =G32-F32 -> 0 | I32: =IF(H32=0,"一致","请调整") -> 一致 | M32: =IF(J32=0,0,(G32*34000+H32*30000+I32*32000)/J32) -> 0 | N32: =IF(J32=0,0,(G32*9000+H32*8500+I32*9000)/J32) -> 0 | O32: =M32-N32 -> 0 | P32: =J32*O32 -> 0 | Q32: =IFERROR(VLOOKUP(A32,'02_线索来源分解'!$A$26:$G$200,7,0)*J32/VLOOKUP(A32,'02_线索来源分解'!$A$26:$G$200,3,0),0) -> 0 | R32: =P32-Q32 -> 0
A33: 上海茸兴店 | B33: =IFERROR(VLOOKUP(A33,'02_线索来源分解'!$A$26:$C$200,3,0),0) -> 32 | C33: =SUMIF($A$6:$A$28,A33,$J$6:$J$28) -> 32 | D33: =C33-B33 -> 0 | E33: =IF(D33=0,"一致","请调整") -> 一致 | F33: =IFERROR(VLOOKUP(A33,'02_线索来源分解'!$A$26:$G$200,7,0),0) -> 235200 | G33: =SUMIF($A$6:$A$28,A33,$Q$6:$Q$28) -> 235200 | H33: =G33-F33 -> 0 | I33: =IF(H33=0,"一致","请调整") -> 一致 | M33: =IF(J33=0,0,(G33*34000+H33*30000+I33*32000)/J33) -> 0 | N33: =IF(J33=0,0,(G33*9000+H33*8500+I33*9000)/J33) -> 0 | O33: =M33-N33 -> 0 | P33: =J33*O33 -> 0 | Q33: =IFERROR(VLOOKUP(A33,'02_线索来源分解'!$A$26:$G$200,7,0)*J33/VLOOKUP(A33,'02_线索来源分解'!$A$26:$G$200,3,0),0) -> 0 | R33: =P33-Q33 -> 0
A34: 上海松江店 | B34: =IFERROR(VLOOKUP(A34,'02_线索来源分解'!$A$26:$C$200,3,0),0) -> 50 | C34: =SUMIF($A$6:$A$28,A34,$J$6:$J$28) -> 50 | D34: =C34-B34 -> 0 | E34: =IF(D34=0,"一致","请调整") -> 一致 | F34: =IFERROR(VLOOKUP(A34,'02_线索来源分解'!$A$26:$G$200,7,0),0) -> 806400 | G34: =SUMIF($A$6:$A$28,A34,$Q$6:$Q$28) -> 806400 | H34: =G34-F34 -> 0 | I34: =IF(H34=0,"一致","请调整") -> 一致 | M34: =IF(J34=0,0,(G34*34000+H34*30000+I34*32000)/J34) -> 0 | N34: =IF(J34=0,0,(G34*9000+H34*8500+I34*9000)/J34) -> 0 | O34: =M34-N34 -> 0 | P34: =J34*O34 -> 0 | Q34: =IFERROR(VLOOKUP(A34,'02_线索来源分解'!$A$26:$G$200,7,0)*J34/VLOOKUP(A34,'02_线索来源分解'!$A$26:$G$200,3,0),0) -> 0 | R34: =P34-Q34 -> 0
A35: 上海龙湖奉贤天街店 | B35: =IFERROR(VLOOKUP(A35,'02_线索来源分解'!$A$26:$C$200,3,0),0) -> 24 | C35: =SUMIF($A$6:$A$28,A35,$J$6:$J$28) -> 24 | D35: =C35-B35 -> 0 | E35: =IF(D35=0,"一致","请调整") -> 一致 | F35: =IFERROR(VLOOKUP(A35,'02_线索来源分解'!$A$26:$G$200,7,0),0) -> 182800 | G35: =SUMIF($A$6:$A$28,A35,$Q$6:$Q$28) -> 182800 | H35: =G35-F35 -> 0 | I35: =IF(H35=0,"一致","请调整") -> 一致 | M35: =IF(J35=0,0,(G35*34000+H35*30000+I35*32000)/J35) -> 0 | N35: =IF(J35=0,0,(G35*9000+H35*8500+I35*9000)/J35) -> 0 | O35: =M35-N35 -> 0 | P35: =J35*O35 -> 0 | Q35: =IFERROR(VLOOKUP(A35,'02_线索来源分解'!$A$26:$G$200,7,0)*J35/VLOOKUP(A35,'02_线索来源分解'!$A$26:$G$200,3,0),0) -> 0 | R35: =P35-Q35 -> 0
A36: 上海沪青平店 | B36: =IFERROR(VLOOKUP(A36,'02_线索来源分解'!$A$26:$C$200,3,0),0) -> 12 | C36: =SUMIF($A$6:$A$28,A36,$J$6:$J$28) -> 12 | D36: =C36-B36 -> 0 | E36: =IF(D36=0,"一致","请调整") -> 一致 | F36: =IFERROR(VLOOKUP(A36,'02_线索来源分解'!$A$26:$G$200,7,0),0) -> 100000 | G36: =SUMIF($A$6:$A$28,A36,$Q$6:$Q$28) -> 100000 | H36: =G36-F36 -> 0 | I36: =IF(H36=0,"一致","请调整") -> 一致 | M36: =IF(J36=0,0,(G36*34000+H36*30000+I36*32000)/J36) -> 0 | N36: =IF(J36=0,0,(G36*9000+H36*8500+I36*9000)/J36) -> 0 | O36: =M36-N36 -> 0 | P36: =J36*O36 -> 0 | Q36: =IFERROR(VLOOKUP(A36,'02_线索来源分解'!$A$26:$G$200,7,0)*J36/VLOOKUP(A36,'02_线索来源分解'!$A$26:$G$200,3,0),0) -> 0 | R36: =P36-Q36 -> 0
A37: 上海中春店 | B37: =IFERROR(VLOOKUP(A37,'02_线索来源分解'!$A$26:$C$200,3,0),0) -> 6 | C37: =SUMIF($A$6:$A$28,A37,$J$6:$J$28) -> 6 | D37: =C37-B37 -> 0 | E37: =IF(D37=0,"一致","请调整") -> 一致 | F37: =IFERROR(VLOOKUP(A37,'02_线索来源分解'!$A$26:$G$200,7,0),0) -> 133500 | G37: =SUMIF($A$6:$A$28,A37,$Q$6:$Q$28) -> 133500 | H37: =G37-F37 -> 0 | I37: =IF(H37=0,"一致","请调整") -> 一致 | M37: =IF(J37=0,0,(G37*34000+H37*30000+I37*32000)/J37) -> 0 | N37: =IF(J37=0,0,(G37*9000+H37*8500+I37*9000)/J37) -> 0 | O37: =M37-N37 -> 0 | P37: =J37*O37 -> 0 | Q37: =IFERROR(VLOOKUP(A37,'02_线索来源分解'!$A$26:$G$200,7,0)*J37/VLOOKUP(A37,'02_线索来源分解'!$A$26:$G$200,3,0),0) -> 0 | R37: =P37-Q37 -> 0

Sheet 04_周执行追踪
A1: 3月周执行追踪表（上海门店）
A2: 按门店目标自动拆分到周；周度费用预算按单店费用均摊，可录入实际值。
A4: 周度目标与达成
A5: 周次 | B5: 日期范围 | C5: 门店 | D5: 周销量目标 | E5: 周库存目标 | F5: 周线索目标 | G5: 实际销量 | H5: 实际库存 | I5: 实际线索 | J5: 销量达成 | K5: 库存达成 | L5: 线索达成 | M5: 周费用预算(元) | N5: 周费用实际(元) | O5: 复盘动作
A6: 第1周 | B6: 3月1日-3月8日 | C6: 上海车市店 | D6: =ROUND(IFERROR(VLOOKUP(C6,'02_线索来源分解'!$A$26:$D$200,3,0)/4,0),0) -> 7 | E6: =ROUND(IFERROR(VLOOKUP(C6,'02_线索来源分解'!$A$26:$D$200,4,0)/4,0),0) -> 3 | F6: =ROUND(IFERROR(VLOOKUP(C6,'02_线索来源分解'!$A$26:$E$200,5,0)/4,0),0) -> 255 | G6: 0 | H6: 0 | I6: 0 | J6: =IF(D6=0,0,G6/D6) -> 0 | K6: =IF(E6=0,0,H6/E6) -> 0 | L6: =IF(F6=0,0,I6/F6) -> 0 | M6: =ROUND(IFERROR(VLOOKUP(C6,'02_线索来源分解'!$A$26:$G$200,7,0)/4,0),0) -> 43600 | N6: 0
A7: 第1周 | B7: 3月1日-3月8日 | C7: 上海茸兴店 | D7: =ROUND(IFERROR(VLOOKUP(C7,'02_线索来源分解'!$A$26:$D$200,3,0)/4,0),0) -> 8 | E7: =ROUND(IFERROR(VLOOKUP(C7,'02_线索来源分解'!$A$26:$D$200,4,0)/4,0),0) -> 3 | F7: =ROUND(IFERROR(VLOOKUP(C7,'02_线索来源分解'!$A$26:$E$200,5,0)/4,0),0) -> 314 | G7: 0 | H7: 0 | I7: 0 | J7: =IF(D7=0,0,G7/D7) -> 0 | K7: =IF(E7=0,0,H7/E7) -> 0 | L7: =IF(F7=0,0,I7/F7) -> 0 | M7: =ROUND(IFERROR(VLOOKUP(C7,'02_线索来源分解'!$A$26:$G$200,7,0)/4,0),0) -> 58800 | N7: 0
A8: 第1周 | B8: 3月1日-3月8日 | C8: 上海松江店 | D8: =ROUND(IFERROR(VLOOKUP(C8,'02_线索来源分解'!$A$26:$D$200,3,0)/4,0),0) -> 13 | E8: =ROUND(IFERROR(VLOOKUP(C8,'02_线索来源分解'!$A$26:$D$200,4,0)/4,0),0) -> 5 | F8: =ROUND(IFERROR(VLOOKUP(C8,'02_线索来源分解'!$A$26:$E$200,5,0)/4,0),0) -> 490 | G8: 0 | H8: 0 | I8: 0 | J8: =IF(D8=0,0,G8/D8) -> 0 | K8: =IF(E8=0,0,H8/E8) -> 0 | L8: =IF(F8=0,0,I8/F8) -> 0 | M8: =ROUND(IFERROR(VLOOKUP(C8,'02_线索来源分解'!$A$26:$G$200,7,0)/4,0),0) -> 201600 | N8: 0
A9: 第1周 | B9: 3月1日-3月8日 | C9: 上海龙湖奉贤天街店 | D9: =ROUND(IFERROR(VLOOKUP(C9,'02_线索来源分解'!$A$26:$D$200,3,0)/4,0),0) -> 6 | E9: =ROUND(IFERROR(VLOOKUP(C9,'02_线索来源分解'!$A$26:$D$200,4,0)/4,0),0) -> 3 | F9: =ROUND(IFERROR(VLOOKUP(C9,'02_线索来源分解'!$A$26:$E$200,5,0)/4,0),0) -> 235 | G9: 0 | H9: 0 | I9: 0 | J9: =IF(D9=0,0,G9/D9) -> 0 | K9: =IF(E9=0,0,H9/E9) -> 0 | L9: =IF(F9=0,0,I9/F9) -> 0 | M9: =ROUND(IFERROR(VLOOKUP(C9,'02_线索来源分解'!$A$26:$G$200,7,0)/4,0),0) -> 45700 | N9: 0
A10: 第1周 | B10: 3月1日-3月8日 | C10: 上海沪青平店 | D10: =ROUND(IFERROR(VLOOKUP(C10,'02_线索来源分解'!$A$26:$D$200,3,0)/4,0),0) -> 3 | E10: =ROUND(IFERROR(VLOOKUP(C10,'02_线索来源分解'!$A$26:$D$200,4,0)/4,0),0) -> 1 | F10: =ROUND(IFERROR(VLOOKUP(C10,'02_线索来源分解'!$A$26:$E$200,5,0)/4,0),0) -> 118 | G10: 0 | H10: 0 | I10: 0 | J10: =IF(D10=0,0,G10/D10) -> 0 | K10: =IF(E10=0,0,H10/E10) -> 0 | L10: =IF(F10=0,0,I10/F10) -> 0 | M10: =ROUND(IFERROR(VLOOKUP(C10,'02_线索来源分解'!$A$26:$G$200,7,0)/4,0),0) -> 25000 | N10: 0
A11: 第1周 | B11: 3月1日-3月8日 | C11: 上海中春店 | D11: =ROUND(IFERROR(VLOOKUP(C11,'02_线索来源分解'!$A$26:$D$200,3,0)/4,0),0) -> 2 | E11: =ROUND(IFERROR(VLOOKUP(C11,'02_线索来源分解'!$A$26:$D$200,4,0)/4,0),0) -> 1 | F11: =ROUND(IFERROR(VLOOKUP(C11,'02_线索来源分解'!$A$26:$E$200,5,0)/4,0),0) -> 59 | G11: 0 | H11: 0 | I11: 0 | J11: =IF(D11=0,0,G11/D11) -> 0 | K11: =IF(E11=0,0,H11/E11) -> 0 | L11: =IF(F11=0,0,I11/F11) -> 0 | M11: =ROUND(IFERROR(VLOOKUP(C11,'02_线索来源分解'!$A$26:$G$200,7,0)/4,0),0) -> 33375 | N11: 0
A12: 第2周 | B12: 3月9日-3月15日 | C12: 上海车市店 | D12: =ROUND(IFERROR(VLOOKUP(C12,'02_线索来源分解'!$A$26:$D$200,3,0)/4,0),0) -> 7 | E12: =ROUND(IFERROR(VLOOKUP(C12,'02_线索来源分解'!$A$26:$D$200,4,0)/4,0),0) -> 3 | F12: =ROUND(IFERROR(VLOOKUP(C12,'02_线索来源分解'!$A$26:$E$200,5,0)/4,0),0) -> 255 | G12: 0 | H12: 0 | I12: 0 | J12: =IF(D12=0,0,G12/D12) -> 0 | K12: =IF(E12=0,0,H12/E12) -> 0 | L12: =IF(F12=0,0,I12/F12) -> 0 | M12: =ROUND(IFERROR(VLOOKUP(C12,'02_线索来源分解'!$A$26:$G$200,7,0)/4,0),0) -> 43600 | N12: 0
A13: 第2周 | B13: 3月9日-3月15日 | C13: 上海茸兴店 | D13: =ROUND(IFERROR(VLOOKUP(C13,'02_线索来源分解'!$A$26:$D$200,3,0)/4,0),0) -> 8 | E13: =ROUND(IFERROR(VLOOKUP(C13,'02_线索来源分解'!$A$26:$D$200,4,0)/4,0),0) -> 3 | F13: =ROUND(IFERROR(VLOOKUP(C13,'02_线索来源分解'!$A$26:$E$200,5,0)/4,0),0) -> 314 | G13: 0 | H13: 0 | I13: 0 | J13: =IF(D13=0,0,G13/D13) -> 0 | K13: =IF(E13=0,0,H13/E13) -> 0 | L13: =IF(F13=0,0,I13/F13) -> 0 | M13: =ROUND(IFERROR(VLOOKUP(C13,'02_线索来源分解'!$A$26:$G$200,7,0)/4,0),0) -> 58800 | N13: 0
A14: 第2周 | B14: 3月9日-3月15日 | C14: 上海松江店 | D14: =ROUND(IFERROR(VLOOKUP(C14,'02_线索来源分解'!$A$26:$D$200,3,0)/4,0),0) -> 13 | E14: =ROUND(IFERROR(VLOOKUP(C14,'02_线索来源分解'!$A$26:$D$200,4,0)/4,0),0) -> 5 | F14: =ROUND(IFERROR(VLOOKUP(C14,'02_线索来源分解'!$A$26:$E$200,5,0)/4,0),0) -> 490 | G14: 0 | H14: 0 | I14: 0 | J14: =IF(D14=0,0,G14/D14) -> 0 | K14: =IF(E14=0,0,H14/E14) -> 0 | L14: =IF(F14=0,0,I14/F14) -> 0 | M14: =ROUND(IFERROR(VLOOKUP(C14,'02_线索来源分解'!$A$26:$G$200,7,0)/4,0),0) -> 201600 | N14: 0
A15: 第2周 | B15: 3月9日-3月15日 | C15: 上海龙湖奉贤天街店 | D15: =ROUND(IFERROR(VLOOKUP(C15,'02_线索来源分解'!$A$26:$D$200,3,0)/4,0),0) -> 6 | E15: =ROUND(IFERROR(VLOOKUP(C15,'02_线索来源分解'!$A$26:$D$200,4,0)/4,0),0) -> 3 | F15: =ROUND(IFERROR(VLOOKUP(C15,'02_线索来源分解'!$A$26:$E$200,5,0)/4,0),0) -> 235 | G15: 0 | H15: 0 | I15: 0 | J15: =IF(D15=0,0,G15/D15) -> 0 | K15: =IF(E15=0,0,H15/E15) -> 0 | L15: =IF(F15=0,0,I15/F15) -> 0 | M15: =ROUND(IFERROR(VLOOKUP(C15,'02_线索来源分解'!$A$26:$G$200,7,0)/4,0),0) -> 45700 | N15: 0
A16: 第2周 | B16: 3月9日-3月15日 | C16: 上海沪青平店 | D16: =ROUND(IFERROR(VLOOKUP(C16,'02_线索来源分解'!$A$26:$D$200,3,0)/4,0),0) -> 3 | E16: =ROUND(IFERROR(VLOOKUP(C16,'02_线索来源分解'!$A$26:$D$200,4,0)/4,0),0) -> 1 | F16: =ROUND(IFERROR(VLOOKUP(C16,'02_线索来源分解'!$A$26:$E$200,5,0)/4,0),0) -> 118 | G16: 0 | H16: 0 | I16: 0 | J16: =IF(D16=0,0,G16/D16) -> 0 | K16: =IF(E16=0,0,H16/E16) -> 0 | L16: =IF(F16=0,0,I16/F16) -> 0 | M16: =ROUND(IFERROR(VLOOKUP(C16,'02_线索来源分解'!$A$26:$G$200,7,0)/4,0),0) -> 25000 | N16: 0
A17: 第2周 | B17: 3月9日-3月15日 | C17: 上海中春店 | D17: =ROUND(IFERROR(VLOOKUP(C17,'02_线索来源分解'!$A$26:$D$200,3,0)/4,0),0) -> 2 | E17: =ROUND(IFERROR(VLOOKUP(C17,'02_线索来源分解'!$A$26:$D$200,4,0)/4,0),0) -> 1 | F17: =ROUND(IFERROR(VLOOKUP(C17,'02_线索来源分解'!$A$26:$E$200,5,0)/4,0),0) -> 59 | G17: 0 | H17: 0 | I17: 0 | J17: =IF(D17=0,0,G17/D17) -> 0 | K17: =IF(E17=0,0,H17/E17) -> 0 | L17: =IF(F17=0,0,I17/F17) -> 0 | M17: =ROUND(IFERROR(VLOOKUP(C17,'02_线索来源分解'!$A$26:$G$200,7,0)/4,0),0) -> 33375 | N17: 0
... A29: 第4周 | B29: 3月24日-3月31日 | C29: 上海中春店 | D29: =ROUND(IFERROR(VLOOKUP(C29,'02_线索来源分解'!$A$26:$D$200,3,0)/4,0),0) -> 2 | E29: =ROUND(IFERROR(VLOOKUP(C29,'02_线索来源分解'!$A$26:$D$200,4,0)/4,0),0) -> 1 | F29: =ROUND(IFERROR(VLOOKUP(C29,'02_线索来源分解'!$A$26:$E$200,5,0)/4,0),0) -> 59 | G29: 0 | H29: 0 | I29: 0 | J29: =IF(D29=0,0,G29/D29) -> 0 | K29: =IF(E29=0,0,H29/E29) -> 0 | L29: =IF(F29=0,0,I29/F29) -> 0 | M29: =ROUND(IFERROR(VLOOKUP(C29,'02_线索来源分解'!$A$26:$G$200,7,0)/4,0),0) -> 33375 | N29: 0

Sheet 05_销售分析排名
A1: 江苏万友上海阿维塔 2026年3月销售人员分析与排名
A2: 数据来源：03_门店顾问分解。排名以“预计经营利润”为主，综合评分=利润50%+销量30%+线索效率20%。
A4: 一、人员经营概览（自动汇总）
A5: 销售顾问人数 | B5: =COUNT(B12:B34) -> 0 | D5: 人均销量目标(台) | E5: =IF(B5=0,0,B6/B5) -> 0
A6: 总销量目标(台) | B6: =SUM(G12:G34) -> 150 | D6: 人均线索目标(条) | E6: =IF(B5=0,0,B7/B5) -> 0
A7: 总线索目标(条) | B7: =SUM(H12:H34) -> 5886 | D7: 人均预计经营利润(元) | E7: =IF(B5=0,0,B8/B5) -> 0
A8: 总预计经营利润(元) | B8: =SUM(J12:J34) -> -627300 | D8: 利润为正人数 | E8: =COUNTIF(J12:J34,">0") -> 3
A10: 二、销售人员分析与排名
A11: 排名 | B11: 门店 | C11: 销售顾问 | D11: 3月07目标 | E11: 3月06目标 | F11: 3月12目标 | G11: 3月合计目标 | H11: 个人线索目标 | I11: 个人库存目标 | J11: 预计经营利润(元) | K11: 利润贡献占比 | L11: 利润排名 | M11: 销量排名 | N11: 线索效率(线索/台) | O11: 效率排名 | P11: 综合得分 | Q11: 综合排名 | R11: 经营建议
A12: =Q12 -> 6 | B12: ='03_门店顾问分解'!A6 -> 上海车市店 | C12: ='03_门店顾问分解'!B6 -> 梁会方 | D12: ='03_门店顾问分解'!G6 -> 4 | E12: ='03_门店顾问分解'!H6 -> 2 | F12: ='03_门店顾问分解'!I6 -> 1 | G12: ='03_门店顾问分解'!J6 -> 7 | H12: ='03_门店顾问分解'!K6 -> 275 | I12: ='03_门店顾问分解'!L6 -> 3 | J12: ='03_门店顾问分解'!R6 -> 4046.1538 | K12: =IF($B$8=0,0,J12/$B$8) -> -0.0064501097 | L12: =_xlfn.RANK.EQ(J12,$J$12:$J$34,0) -> 1 | M12: =_xlfn.RANK.EQ(G12,$G$12:$G$34,0) -> 9 | N12: =IF(G12=0,0,H12/G12) -> 39.285714 | O12: =_xlfn.RANK.EQ(N12,$N$12:$N$34,1) -> 14 | P12: =IFERROR(((J12-MIN($J$12:$J$34))/(MAX($J$12:$J$34)-MIN($J$12:$J$34))*50)+((G12-MIN($G$12:$G$34))/(MAX($G$12:$G$34)-MIN($G$12:$G$34))*30)+((MAX($N$12:$N$34)-N12)/(MAX($N$12:$N$34)-MIN($N$12:$N$34))*20),0) -> 81.607143 | Q12: =_xlfn.RANK.EQ(P12,$P$12:$P$34,0) -> 6 | R12: =IF(J12<0,"优先帮扶：优化费用与线索质量",IF(Q12<=5,"重点冲刺：保持高产并带教",IF(Q12<=12,"稳态提升：强化库存去化","跟进改善：提升转化效率"))) -> 稳态提升：强化库存去化
A13: =Q13 -> 11 | B13: ='03_门店顾问分解'!A7 -> 上海车市店 | C13: ='03_门店顾问分解'!B7 -> 王毅洋 | D13: ='03_门店顾问分解'!G7 -> 3 | E13: ='03_门店顾问分解'!H7 -> 3 | F13: ='03_门店顾问分解'!I7 -> 1 | G13: ='03_门店顾问分解'!J7 -> 7 | H13: ='03_门店顾问分解'!K7 -> 275 | I13: ='03_门店顾问分解'!L7 -> 3 | J13: ='03_门店顾问分解'!R7 -> -4453.8462 | K13: =IF($B$8=0,0,J13/$B$8) -> 0.0071000258 | L13: =_xlfn.RANK.EQ(J13,$J$12:$J$34,0) -> 11 | M13: =_xlfn.RANK.EQ(G13,$G$12:$G$34,0) -> 9 | N13: =IF(G13=0,0,H13/G13) -> 39.285714 | O13: =_xlfn.RANK.EQ(N13,$N$12:$N$34,1) -> 14 | P13: =IFERROR(((J13-MIN($J$12:$J$34))/(MAX($J$12:$J$34)-MIN($J$12:$J$34))*50)+((G13-MIN($G$12:$G$34))/(MAX($G$12:$G$34)-MIN($G$12:$G$34))*30)+((MAX($N$12:$N$34)-N13)/(MAX($N$12:$N$34)-MIN($N$12:$N$34))*20),0) -> 77.284793 | Q13: =_xlfn.RANK.EQ(P13,$P$12:$P$34,0) -> 11 | R13: =IF(J13<0,"优先帮扶：优化费用与线索质量",IF(Q13<=5,"重点冲刺：保持高产并带教",IF(Q13<=12,"稳态提升：强化库存去化","跟进改善：提升转化效率"))) -> 优先帮扶：优化费用与线索质量
A14: =Q14 -> 1 | B14: ='03_门店顾问分解'!A8 -> 上海车市店 | C14: ='03_门店顾问分解'!B8 -> 马星晨 | D14: ='03_门店顾问分解'!G8 -> 3 | E14: ='03_门店顾问分解'!H8 -> 3 | F14: ='03_门店顾问分解'!I8 -> 0 | G14: ='03_门店顾问分解'!J8 -> 6 | H14: ='03_门店顾问分解'!K8 -> 235 | I14: ='03_门店顾问分解'!L8 -> 2 | J14: ='03_门店顾问分解'!R8 -> 253.84615 | K14: =IF($B$8=0,0,J14/$B$8) -> -0.00040466468 | L14: =_xlfn.RANK.EQ(J14,$J$12:$J$34,0) -> 3 | M14: =_xlfn.RANK.EQ(G14,$G$12:$G$34,0) -> 14 | N14: =IF(G14=0,0,H14/G14) -> 39.166667 | O14: =_xlfn.RANK.EQ(N14,$N$12:$N$34,1) -> 1 | P14: =IFERROR(((J14-MIN($J$12:$J$34))/(MAX($J$12:$J$34)-MIN($J$12:$J$34))*50)+((G14-MIN($G$12:$G$34))/(MAX($G$12:$G$34)-MIN($G$12:$G$34))*30)+((MAX($N$12:$N$34)-N14)/(MAX($N$12:$N$34)-MIN($N$12:$N$34))*20),0) -> 83.071567 | Q14: =_xlfn.RANK.EQ(P14,$P$12:$P$34,0) -> 1 | R14: =IF(J14<0,"优先帮扶：优化费用与线索质量",IF(Q14<=5,"重点冲刺：保持高产并带教",IF(Q14<=12,"稳态提升：强化库存去化","跟进改善：提升转化效率"))) -> 重点冲刺：保持高产并带教
A15: =Q15 -> 2 | B15: ='03_门店顾问分解'!A9 -> 上海车市店 | C15: ='03_门店顾问分解'!B9 -> 王明龙 | D15: ='03_门店顾问分解'!G9 -> 3 | E15: ='03_门店顾问分解'!H9 -> 2 | F15: ='03_门店顾问分解'!I9 -> 1 | G15: ='03_门店顾问分解'!J9 -> 6 | H15: ='03_门店顾问分解'!K9 -> 235 | I15: ='03_门店顾问分解'!L9 -> 2 | J15: ='03_门店顾问分解'!R9 -> -246.15385 | K15: =IF($B$8=0,0,J15/$B$8) -> 0.00039240211 | L15: =_xlfn.RANK.EQ(J15,$J$12:$J$34,0) -> 4 | M15: =_xlfn.RANK.EQ(G15,$G$12:$G$34,0) -> 14 | N15: =IF(G15=0,0,H15/G15) -> 39.166667 | O15: =_xlfn.RANK.EQ(N15,$N$12:$N$34,1) -> 1 | P15: =IFERROR(((J15-MIN($J$12:$J$34))/(MAX($J$12:$J$34)-MIN($J$12:$J$34))*50)+((G15-MIN($G$12:$G$34))/(MAX($G$12:$G$34)-MIN($G$12:$G$34))*30)+((MAX($N$12:$N$34)-N15)/(MAX($N$12:$N$34)-MIN($N$12:$N$34))*20),0) -> 82.817311 | Q15: =_xlfn.RANK.EQ(P15,$P$12:$P$34,0) -> 2 | R15: =IF(J15<0,"优先帮扶：优化费用与线索质量",IF(Q15<=5,"重点冲刺：保持高产并带教",IF(Q15<=12,"稳态提升：强化库存去化","跟进改善：提升转化效率"))) -> 优先帮扶：优化费用与线索质量
A16: =Q16 -> 8 | B16: ='03_门店顾问分解'!A10 -> 上海茸兴店 | C16: ='03_门店顾问分解'!B10 -> 李宋坚 | D16: ='03_门店顾问分解'!G10 -> 4 | E16: ='03_门店顾问分解'!H10 -> 2 | F16: ='03_门店顾问分解'!I10 -> 1 | G16: ='03_门店顾问分解'!J10 -> 7 | H16: ='03_门店顾问分解'!K10 -> 275 | I16: ='03_门店顾问分解'!L10 -> 3 | J16: ='03_门店顾问分解'!R10 -> -450 | K16: =IF($B$8=0,0,J16/$B$8) -> 0.00071736011 | L16: =_xlfn.RANK.EQ(J16,$J$12:$J$34,0) -> 5 | M16: =_xlfn.RANK.EQ(G16,$G$12:$G$34,0) -> 9 | N16: =IF(G16=0,0,H16/G16) -> 39.285714 | O16: =_xlfn.RANK.EQ(N16,$N$12:$N$34,1) -> 14 | P16: =IFERROR(((J16-MIN($J$12:$J$34))/(MAX($J$12:$J$34)-MIN($J$12:$J$34))*50)+((G16-MIN($G$12:$G$34))/(MAX($G$12:$G$34)-MIN($G$12:$G$34))*30)+((MAX($N$12:$N$34)-N16)/(MAX($N$12:$N$34)-MIN($N$12:$N$34))*20),0) -> 79.320796 | Q16: =_xlfn.RANK.EQ(P16,$P$12:$P$34,0) -> 8 | R16: =IF(J16<0,"优先帮扶：优化费用与线索质量",IF(Q16<=5,"重点冲刺：保持高产并带教",IF(Q16<=12,"稳态提升：强化库存去化","跟进改善：提升转化效率"))) -> 优先帮扶：优化费用与线索质量
A17: =Q17 -> 12 | B17: ='03_门店顾问分解'!A11 -> 上海茸兴店 | C17: ='03_门店顾问分解'!B11 -> 顾浩 | D17: ='03_门店顾问分解'!G11 -> 3 | E17: ='03_门店顾问分解'!H11 -> 3 | F17: ='03_门店顾问分解'!I11 -> 1 | G17: ='03_门店顾问分解'!J11 -> 7 | H17: ='03_门店顾问分解'!K11 -> 275 | I17: ='03_门店顾问分解'!L11 -> 3 | J17: ='03_门店顾问分解'!R11 -> -8950 | K17: =IF($B$8=0,0,J17/$B$8) -> 0.014267496 | L17: =_xlfn.RANK.EQ(J17,$J$12:$J$34,0) -> 15 | M17: =_xlfn.RANK.EQ(G17,$G$12:$G$34,0) -> 9 | N17: =IF(G17=0,0,H17/G17) -> 39.285714 | O17: =_xlfn.RANK.EQ(N17,$N$12:$N$34,1) -> 14 | P17: =IFERROR(((J17-MIN($J$12:$J$34))/(MAX($J$12:$J$34)-MIN($J$12:$J$34))*50)+((G17-MIN($G$12:$G$34))/(MAX($G$12:$G$34)-MIN($G$12:$G$34))*30)+((MAX($N$12:$N$34)-N17)/(MAX($N$12:$N$34)-MIN($N$12:$N$34))*20),0) -> 74.998447 | Q17: =_xlfn.RANK.EQ(P17,$P$12:$P$34,0) -> 12 | R17: =IF(J17<0,"优先帮扶：优化费用与线索质量",IF(Q17<=5,"重点冲刺：保持高产并带教",IF(Q17<=12,"稳态提升：强化库存去化","跟进改善：提升转化效率"))) -> 优先帮扶：优化费用与线索质量
A18: =Q18 -> 8 | B18: ='03_门店顾问分解'!A12 -> 上海茸兴店 | C18: ='03_门店顾问分解'!B12 -> 符陆彬 | D18: ='03_门店顾问分解'!G12 -> 4 | E18: ='03_门店顾问分解'!H12 -> 2 | F18: ='03_门店顾问分解'!I12 -> 1 | G18: ='03_门店顾问分解'!J12 -> 7 | H18: ='03_门店顾问分解'!K12 -> 275 | I18: ='03_门店顾问分解'!L12 -> 3 | J18: ='03_门店顾问分解'!R12 -> -450 | K18: =IF($B$8=0,0,J18/$B$8) -> 0.00071736011 | L18: =_xlfn.RANK.EQ(J18,$J$12:$J$34,0) -> 5 | M18: =_xlfn.RANK.EQ(G18,$G$12:$G$34,0) -> 9 | N18: =IF(G18=0,0,H18/G18) -> 39.285714 | O18: =_xlfn.RANK.EQ(N18,$N$12:$N$34,1) -> 14 | P18: =IFERROR(((J18-MIN($J$12:$J$34))/(MAX($J$12:$J$34)-MIN($J$12:$J$34))*50)+((G18-MIN($G$12:$G$34))/(MAX($G$12:$G$34)-MIN($G$12:$G$34))*30)+((MAX($N$12:$N$34)-N18)/(MAX($N$12:$N$34)-MIN($N$12:$N$34))*20),0) -> 79.320796 | Q18: =_xlfn.RANK.EQ(P18,$P$12:$P$34,0) -> 8 | R18: =IF(J18<0,"优先帮扶：优化费用与线索质量",IF(Q18<=5,"重点冲刺：保持高产并带教",IF(Q18<=12,"稳态提升：强化库存去化","跟进改善：提升转化效率"))) -> 优先帮扶：优化费用与线索质量
A19: =Q19 -> 7 | B19: ='03_门店顾问分解'!A13 -> 上海茸兴店 | C19: ='03_门店顾问分解'!B13 -> 高宏展 | D19: ='03_门店顾问分解'!G13 -> 3 | E19: ='03_门店顾问分解'!H13 -> 3 | F19: ='03_门店顾问分解'!I13 -> 0 | G19: ='03_门店顾问分解'!J13 -> 6 | H19: ='03_门店顾问分解'!K13 -> 235 | I19: ='03_门店顾问分解'!L13 -> 2 | J19: ='03_门店顾问分解'!R13 -> -3600 | K19: =IF($B$8=0,0,J19/$B$8) -> 0.0057388809 | L19: =_xlfn.RANK.EQ(J19,$J$12:$J$34,0) -> 10 | M19: =_xlfn.RANK.EQ(G19,$G$12:$G$34,0) -> 14 | N19: =IF(G19=0,0,H19/G19) -> 39.166667 | O19: =_xlfn.RANK.EQ(N19,$N$12:$N$34,1) -> 1 | P19: =IFERROR(((J19-MIN($J$12:$J$34))/(MAX($J$12:$J$34)-MIN($J$12:$J$34))*50)+((G19-MIN($G$12:$G$34))/(MAX($G$12:$G$34)-MIN($G$12:$G$34))*30)+((MAX($N$12:$N$34)-N19)/(MAX($N$12:$N$34)-MIN($N$12:$N$34))*20),0) -> 81.111841 | Q19: =_xlfn.RANK.EQ(P19,$P$12:$P$34,0) -> 7 | R19: =IF(J19<0,"优先帮扶：优化费用与线索质量",IF(Q19<=5,"重点冲刺：保持高产并带教",IF(Q19<=12,"稳态提升：强化库存去化","跟进改善：提升转化效率"))) -> 优先帮扶：优化费用与线索质量
A20: =Q20 -> 10 | B20: ='03_门店顾问分解'!A14 -> 上海茸兴店 | C20: ='03_门店顾问分解'!B14 -> 田汨龙 | D20: ='03_门店顾问分解'!G14 -> 3 | E20: ='03_门店顾问分解'!H14 -> 2 | F20: ='03_门店顾问分解'!I14 -> 0 | G20: ='03_门店顾问分解'!J14 -> 5 | H20: ='03_门店顾问分解'!K14 -> 196 | I20: ='03_门店顾问分解'!L14 -> 2 | J20: ='03_门店顾问分解'!R14 -> 1250 | K20: =IF($B$8=0,0,J20/$B$8) -> -0.001992667 | L20: =_xlfn.RANK.EQ(J20,$J$12:$J$34,0) -> 2 | M20: =_xlfn.RANK.EQ(G20,$G$12:$G$34,0) -> 18 | N20: =IF(G20=0,0,H20/G20) -> 39.2 | O20: =_xlfn.RANK.EQ(N20,$N$12:$N$34,1) -> 5 | P20: =IFERROR(((J20-MIN($J$12:$J$34))/(MAX($J$12:$J$34)-MIN($J$12:$J$34))*50)+((G20-MIN($G$12:$G$34))/(MAX($G$12:$G$34)-MIN($G$12:$G$34))*30)+((MAX($N$12:$N$34)-N20)/(MAX($N$12:$N$34)-MIN($N$12:$N$34))*20),0) -> 77.828123 | Q20: =_xlfn.RANK.EQ(P20,$P$12:$P$34,0) -> 10 | R20: =IF(J20<0,"优先帮扶：优化费用与线索质量",IF(Q20<=5,"重点冲刺：保持高产并带教",IF(Q20<=12,"稳态提升：强化库存去化","跟进改善：提升转化效率"))) -> 稳态提升：强化库存去化
A21: =Q21 -> 15 | B21: ='03_门店顾问分解'!A15 -> 上海松江店 | C21: ='03_门店顾问分解'!B15 -> 武利海 | D21: ='03_门店顾问分解'!G15 -> 5 | E21: ='03_门店顾问分解'!H15 -> 4 | F21: ='03_门店顾问分解'!I15 -> 1 | G21: ='03_门店顾问分解'!J15 -> 10 | H21: ='03_门店顾问分解'!K15 -> 392 | I21: ='03_门店顾问分解'!L15 -> 4 | J21: ='03_门店顾问分解'!R15 -> -94280 | K21: =IF($B$8=0,0,J21/$B$8) -> 0.15029491 | L21: =_xlfn.RANK.EQ(J21,$J$12:$J$34,0) -> 19 | M21: =_xlfn.RANK.EQ(G21,$G$12:$G$34,0) -> 1 | N21: =IF(G21=0,0,H21/G21) -> 39.2 | O21: =_xlfn.RANK.EQ(N21,$N$12:$N$34,1) -> 5 | P21: =IFERROR(((J21-MIN($J$12:$J$34))/(MAX($J$12:$J$34)-MIN($J$12:$J$34))*50)+((G21-MIN($G$12:$G$34))/(MAX($G$12:$G$34)-MIN($G$12:$G$34))*30)+((MAX($N$12:$N$34)-N21)/(MAX($N$12:$N$34)-MIN($N$12:$N$34))*20),0) -> 48 | Q21: =_xlfn.RANK.EQ(P21,$P$12:$P$34,0) -> 15 | R21: =IF(J21<0,"优先帮扶：优化费用与线索质量",IF(Q21<=5,"重点冲刺：保持高产并带教",IF(Q21<=12,"稳态提升：强化库存去化","跟进改善：提升转化效率"))) -> 优先帮扶：优化费用与线索质量
A22: =Q22 -> 15 | B22: ='03_门店顾问分解'!A16 -> 上海松江店 | C22: ='03_门店顾问分解'!B16 -> 黄大海 | D22: ='03_门店顾问分解'!G16 -> 5 | E22: ='03_门店顾问分解'!H16 -> 4 | F22: ='03_门店顾问分解'!I16 -> 1 | G22: ='03_门店顾问分解'!J16 -> 10 | H22: ='03_门店顾问分解'!K16 -> 392 | I22: ='03_门店顾问分解'!L16 -> 4 | J22: ='03_门店顾问分解'!R16 -> -94280 | K22: =IF($B$8=0,0,J22/$B$8) -> 0.15029491 | L22: =_xlfn.RANK.EQ(J22,$J$12:$J$34,0) -> 19 | M22: =_xlfn.RANK.EQ(G22,$G$12:$G$34,0) -> 1 | N22: =IF(G22=0,0,H22/G22) -> 39.2 | O22: =_xlfn.RANK.EQ(N22,$N$12:$N$34,1) -> 5 | P22: =IFERROR(((J22-MIN($J$12:$J$34))/(MAX($J$12:$J$34)-MIN($J$12:$J$34))*50)+((G22-MIN($G$12:$G$34))/(MAX($G$12:$G$34)-MIN($G$12:$G$34))*30)+((MAX($N$12:$N$34)-N22)/(MAX($N$12:$N$34)-MIN($N$12:$N$34))*20),0) -> 48 | Q22: =_xlfn.RANK.EQ(P22,$P$12:$P$34,0) -> 15 | R22: =IF(J22<0,"优先帮扶：优化费用与线索质量",IF(Q22<=5,"重点冲刺：保持高产并带教",IF(Q22<=12,"稳态提升：强化库存去化","跟进改善：提升转化效率"))) -> 优先帮扶：优化费用与线索质量
A23: =Q23 -> 15 | B23: ='03_门店顾问分解'!A17 -> 上海松江店 | C23: ='03_门店顾问分解'!B17 -> 高荟萃 | D23: ='03_门店顾问分解'!G17 -> 5 | E23: ='03_门店顾问分解'!H17 -> 4 | F23: ='03_门店顾问分解'!I17 -> 1 | G23: ='03_门店顾问分解'!J17 -> 10 | H23: ='03_门店顾问分解'!K17 -> 392 | I23: ='03_门店顾问分解'!L17 -> 4 | J23: ='03_门店顾问分解'!R17 -> -94280 | K23: =IF($B$8=0,0,J23/$B$8) -> 0.15029491 | L23: =_xlfn.RANK.EQ(J23,$J$12:$J$34,0) -> 19 | M23: =_xlfn.RANK.EQ(G23,$G$12:$G$34,0) -> 1 | N23: =IF(G23=0,0,H23/G23) -> 39.2 | O23: =_xlfn.RANK.EQ(N23,$N$12:$N$34,1) -> 5 | P23: =IFERROR(((J23-MIN($J$12:$J$34))/(MAX($J$12:$J$34)-MIN($J$12:$J$34))*50)+((G23-MIN($G$12:$G$34))/(MAX($G$12:$G$34)-MIN($G$12:$G$34))*30)+((MAX($N$12:$N$34)-N23)/(MAX($N$12:$N$34)-MIN($N$12:$N$34))*20),0) -> 48 | Q23: =_xlfn.RANK.EQ(P23,$P$12:$P$34,0) -> 15 | R23: =IF(J23<0,"优先帮扶：优化费用与线索质量",IF(Q23<=5,"重点冲刺：保持高产并带教",IF(Q23<=12,"稳态提升：强化库存去化","跟进改善：提升转化效率"))) -> 优先帮扶：优化费用与线索质量
... A34: =Q34 -> 23 | B34: ='03_门店顾问分解'!A28 -> 上海中春店 | C34: ='03_门店顾问分解'!B28 -> 鲁平 | D34: ='03_门店顾问分解'!G28 -> 3 | E34: ='03_门店顾问分解'!H28 -> 3 | F34: ='03_门店顾问分解'!I28 -> 0 | G34: ='03_门店顾问分解'!J28 -> 6 | H34: ='03_门店顾问分解'!K28 -> 235 | I34: ='03_门店顾问分解'!L28 -> 2 | J34: ='03_门店顾问分解'!R28 -> -93000 | K34: =IF($B$8=0,0,J34/$B$8) -> 0.14825442 | L34: =_xlfn.RANK.EQ(J34,$J$12:$J$34,0) -> 18 | M34: =_xlfn.RANK.EQ(G34,$G$12:$G$34,0) -> 14 | N34: =IF(G34=0,0,H34/G34) -> 39.166667 | O34: =_xlfn.RANK.EQ(N34,$N$12:$N$34,1) -> 1 | P34: =IFERROR(((J34-MIN($J$12:$J$34))/(MAX($J$12:$J$34)-MIN($J$12:$J$34))*50)+((G34-MIN($G$12:$G$34))/(MAX($G$12:$G$34)-MIN($G$12:$G$34))*30)+((MAX($N$12:$N$34)-N34)/(MAX($N$12:$N$34)-MIN($N$12:$N$34))*20),0) -> 35.650895 | Q34: =_xlfn.RANK.EQ(P34,$P$12:$P$34,0) -> 23 | R34: =IF(J34<0,"优先帮扶：优化费用与线索质量",IF(Q34<=5,"重点冲刺：保持高产并带教",IF(Q34<=12,"稳态提升：强化库存去化","跟进改善：提升转化效率"))) -> 优先帮扶：优化费用与线索质量
A35: 合计/均值 | D35: =SUM(D12:D34) -> 75 | E35: =SUM(E12:E34) -> 60 | F35: =SUM(F12:F34) -> 15 | G35: =SUM(G12:G34) -> 150 | H35: =SUM(H12:H34) -> 5886 | I35: =SUM(I12:I34) -> 59 | J35: =SUM(J12:J34) -> -627300 | K35: =SUM(K12:K34) -> 1 | N35: =AVERAGE(N12:N34) -> 39.270083 | P35: =AVERAGE(P12:P34) -> 64.824932
A38: 三、TOP5与待提升名单
A39: TOP5（按综合排名） | J39: 待提升5人（按综合排名）
A40: 排名 | B40: 门店 | C40: 顾问 | D40: 预计经营利润 | E40: 综合得分 | J40: 排名 | K40: 门店 | L40: 顾问 | M40: 预计经营利润 | N40: 综合得分
A41: 1 | B41: =IFERROR(INDEX($B$12:$B$34,MATCH(A41,$Q$12:$Q$34,0)),"") -> 上海车市店 | C41: =IFERROR(INDEX($C$12:$C$34,MATCH(A41,$Q$12:$Q$34,0)),"") -> 马星晨 | D41: =IFERROR(INDEX($J$12:$J$34,MATCH(A41,$Q$12:$Q$34,0)),0) -> 253.84615 | E41: =IFERROR(INDEX($P$12:$P$34,MATCH(A41,$Q$12:$Q$34,0)),0) -> 83.071567 | J41: =ROWS($A$1:$A$1) -> 1 | K41: =IFERROR(INDEX($B$12:$B$34,MATCH($B$5-J41+1,$Q$12:$Q$34,0)),"") | L41: =IFERROR(INDEX($C$12:$C$34,MATCH($B$5-J41+1,$Q$12:$Q$34,0)),"") | M41: =IFERROR(INDEX($J$12:$J$34,MATCH($B$5-J41+1,$Q$12:$Q$34,0)),0) -> 0 | N41: =IFERROR(INDEX($P$12:$P$34,MATCH($B$5-J41+1,$Q$12:$Q$34,0)),0) -> 0
A42: 2 | B42: =IFERROR(INDEX($B$12:$B$34,MATCH(A42,$Q$12:$Q$34,0)),"") -> 上海车市店 | C42: =IFERROR(INDEX($C$12:$C$34,MATCH(A42,$Q$12:$Q$34,0)),"") -> 王明龙 | D42: =IFERROR(INDEX($J$12:$J$34,MATCH(A42,$Q$12:$Q$34,0)),0) -> -246.15385 | E42: =IFERROR(INDEX($P$12:$P$34,MATCH(A42,$Q$12:$Q$34,0)),0) -> 82.817311 | J42: =ROWS($A$1:$A$2) -> 2 | K42: =IFERROR(INDEX($B$12:$B$34,MATCH($B$5-J42+1,$Q$12:$Q$34,0)),"") | L42: =IFERROR(INDEX($C$12:$C$34,MATCH($B$5-J42+1,$Q$12:$Q$34,0)),"") | M42: =IFERROR(INDEX($J$12:$J$34,MATCH($B$5-J42+1,$Q$12:$Q$34,0)),0) -> 0 | N42: =IFERROR(INDEX($P$12:$P$34,MATCH($B$5-J42+1,$Q$12:$Q$34,0)),0) -> 0
A43: 3 | B43: =IFERROR(INDEX($B$12:$B$34,MATCH(A43,$Q$12:$Q$34,0)),"") -> 上海龙湖奉贤天街店 | C43: =IFERROR(INDEX($C$12:$C$34,MATCH(A43,$Q$12:$Q$34,0)),"") -> 陆佳乐 | D43: =IFERROR(INDEX($J$12:$J$34,MATCH(A43,$Q$12:$Q$34,0)),0) -> -6933.3333 | E43: =IFERROR(INDEX($P$12:$P$34,MATCH(A43,$Q$12:$Q$34,0)),0) -> 81.916802 | J43: =ROWS($A$1:$A$3) -> 3 | K43: =IFERROR(INDEX($B$12:$B$34,MATCH($B$5-J43+1,$Q$12:$Q$34,0)),"") | L43: =IFERROR(INDEX($C$12:$C$34,MATCH($B$5-J43+1,$Q$12:$Q$34,0)),"") | M43: =IFERROR(INDEX($J$12:$J$34,MATCH($B$5-J43+1,$Q$12:$Q$34,0)),0) -> 0 | N43: =IFERROR(INDEX($P$12:$P$34,MATCH($B$5-J43+1,$Q$12:$Q$34,0)),0) -> 0
A44: 4 | B44: =IFERROR(INDEX($B$12:$B$34,MATCH(A44,$Q$12:$Q$34,0)),"") -> 上海龙湖奉贤天街店 | C44: =IFERROR(INDEX($C$12:$C$34,MATCH(A44,$Q$12:$Q$34,0)),"") -> 陈佳庆 | D44: =IFERROR(INDEX($J$12:$J$34,MATCH(A44,$Q$12:$Q$34,0)),0) -> -7433.3333 | E44: =IFERROR(INDEX($P$12:$P$34,MATCH(A44,$Q$12:$Q$34,0)),0) -> 81.662546 | J44: =ROWS($A$1:$A$4) -> 4 | K44: =IFERROR(INDEX($B$12:$B$34,MATCH($B$5-J44+1,$Q$12:$Q$34,0)),"") | L44: =IFERROR(INDEX($C$12:$C$34,MATCH($B$5-J44+1,$Q$12:$Q$34,0)),"") | M44: =IFERROR(INDEX($J$12:$J$34,MATCH($B$5-J44+1,$Q$12:$Q$34,0)),0) -> 0 | N44: =IFERROR(INDEX($P$12:$P$34,MATCH($B$5-J44+1,$Q$12:$Q$34,0)),0) -> 0
A45: 5 | B45: =IFERROR(INDEX($B$12:$B$34,MATCH(A45,$Q$12:$Q$34,0)),"") | C45: =IFERROR(INDEX($C$12:$C$34,MATCH(A45,$Q$12:$Q$34,0)),"") | D45: =IFERROR(INDEX($J$12:$J$34,MATCH(A45,$Q$12:$Q$34,0)),0) -> 0 | E45: =IFERROR(INDEX($P$12:$P$34,MATCH(A45,$Q$12:$Q$34,0)),0) -> 0 | J45: =ROWS($A$1:$A$5) -> 5 | K45: =IFERROR(INDEX($B$12:$B$34,MATCH($B$5-J45+1,$Q$12:$Q$34,0)),"") | L45: =IFERROR(INDEX($C$12:$C$34,MATCH($B$5-J45+1,$Q$12:$Q$34,0)),"") | M45: =IFERROR(INDEX($J$12:$J$34,MATCH($B$5-J45+1,$Q$12:$Q$34,0)),0) -> 0 | N45: =IFERROR(INDEX($P$12:$P$34,MATCH($B$5-J45+1,$Q$12:$Q$34,0)),0) -> 0
